mini_pandas/__init__.py
mini_pandas/constants.py
mini_pandas/dataframe.py
mini_pandas/pandas_api.py
mini_pandas/str_utils.py
mini_pandas-0.1.0.dist-info/LICENSE
mini_pandas-0.1.0.dist-info/METADATA
mini_pandas-0.1.0.dist-info/WHEEL
mini_pandas-0.1.0.dist-info/top_level.txt
mini_pandas-0.1.0.dist-info/RECORD
