Metadata-Version: 2.1
Name: mini-pandas
Version: 0.1.0
Summary: Custom implementation of `pandas` library
Author-email: Kaloyan Ivanov <kaloyan.ivanov88@gmail.com>
License: MIT License
Requires-Python: >=3.11
License-File: LICENSE
Requires-Dist: numpy ==1.26.4
Provides-Extra: dev
Requires-Dist: tox ==4.15.0 ; extra == 'dev'
Requires-Dist: black ==24.4.2 ; extra == 'dev'
Requires-Dist: pytest ==8.1.1 ; extra == 'dev'
